YiqiXueKoa/README.md
YiqiXueKoa/__init__.py
YiqiXueKoa/__main__.py
YiqiXueKoa/file.epub
YiqiXueKoa/index.html
YiqiXueKoa/css/__init__.py
YiqiXueKoa/css/annotations.css
YiqiXueKoa/css/main.css
YiqiXueKoa/css/normalize.css
YiqiXueKoa/css/popup.css
YiqiXueKoa/font/__init__.py
YiqiXueKoa/font/fontello.eot
YiqiXueKoa/font/fontello.svg
YiqiXueKoa/font/fontello.ttf
YiqiXueKoa/font/fontello.woff
YiqiXueKoa/img/__init__.py
YiqiXueKoa/img/annotator-glyph-sprite.png
YiqiXueKoa/img/annotator-icon-sprite.png
YiqiXueKoa/img/apple-touch-icon.png
YiqiXueKoa/img/cancelfullscreen.png
YiqiXueKoa/img/close.png
YiqiXueKoa/img/fullscreen.png
YiqiXueKoa/img/loader.gif
YiqiXueKoa/img/menu-icon.png
YiqiXueKoa/img/save.png
YiqiXueKoa/img/saved.png
YiqiXueKoa/img/settings-s.png
YiqiXueKoa/img/settings.png
YiqiXueKoa/img/star.png
YiqiXueKoa/js/__init__.py
YiqiXueKoa/js/epub.js
YiqiXueKoa/js/epub.min.js
YiqiXueKoa/js/epub.min.map
YiqiXueKoa/js/hooks.min.js
YiqiXueKoa/js/hooks.min.map
YiqiXueKoa/js/reader.js
YiqiXueKoa/js/reader.js.map
YiqiXueKoa/js/reader.min.js
YiqiXueKoa/js/reader.min.map
YiqiXueKoa/js/hooks/__init__.py
YiqiXueKoa/js/hooks/extensions/__init__.py
YiqiXueKoa/js/hooks/extensions/highlight.js
YiqiXueKoa/js/libs/__init__.py
YiqiXueKoa/js/libs/jquery.min.js
YiqiXueKoa/js/libs/localforage.min.js
YiqiXueKoa/js/libs/screenfull.js
YiqiXueKoa/js/libs/screenfull.min.js
YiqiXueKoa/js/libs/zip.min.js
YiqiXueKoa/js/plugins/__init__.py
YiqiXueKoa/js/plugins/hypothesis.js
YiqiXueKoa/js/plugins/search.js
yiqi_xue_koa-2024.3.2.0.dist-info/METADATA
yiqi_xue_koa-2024.3.2.0.dist-info/WHEEL
yiqi_xue_koa-2024.3.2.0.dist-info/entry_points.txt
yiqi_xue_koa-2024.3.2.0.dist-info/top_level.txt
yiqi_xue_koa-2024.3.2.0.dist-info/RECORD
